{
    "prdId": "prd_001",
    "prdUserId": "user_001",
    "prdName": "Áo khoác",
    "prdCateId": "prd_001",
    "prdSubId": "prd_001",
    "prdPriceOrigin": 55000,
    "prdOrigin": "country-01",
    "prdDateManufacture" : "23/07/2000 - Ngay san xuat",
    "prdDateCreate": "23/07/2000 - Ngay Dang",
    "prdDateExpiry": "23/07/2000 - Ngay Het Han",
    "prdMonthWarranty": "24 Thoi gian bao hanh",
    "prdShortDes": "Mo ta ngan",
    "prdLongDes": "Mo ta dai",
    "prdSale": 0,
    "prdImages": [
        "image1",
        "image2",
        "image3"
    ],
    "prdReact" : 0,
    "prdStatus" : "WAITING_FOR_ACCEPT | AVAILABLE | OUT OF STOCK | STOP",
    "prdNumberInStorage": 34
}